dwgdbserver/.DS_Store
dwgdbserver/__init__.py
dwgdbserver/deviceinfo/.DS_Store
dwgdbserver/deviceinfo/__init__.py
dwgdbserver/deviceinfo/collect.py
dwgdbserver/deviceinfo/devices/alldevices.py
dwgdbserver/deviceinfo/devices/at90pwm1.py
dwgdbserver/deviceinfo/devices/at90pwm161.py
dwgdbserver/deviceinfo/devices/at90pwm216.py
dwgdbserver/deviceinfo/devices/at90pwm2b.py
dwgdbserver/deviceinfo/devices/at90pwm3.py
dwgdbserver/deviceinfo/devices/at90pwm316.py
dwgdbserver/deviceinfo/devices/at90pwm3b.py
dwgdbserver/deviceinfo/devices/at90pwm81.py
dwgdbserver/deviceinfo/devices/at90usb162.py
dwgdbserver/deviceinfo/devices/at90usb82.py
dwgdbserver/deviceinfo/devices/atmega168.py
dwgdbserver/deviceinfo/devices/atmega168a.py
dwgdbserver/deviceinfo/devices/atmega168p.py
dwgdbserver/deviceinfo/devices/atmega168pa.py
dwgdbserver/deviceinfo/devices/atmega168pb.py
dwgdbserver/deviceinfo/devices/atmega16hva.py
dwgdbserver/deviceinfo/devices/atmega16hvb.py
dwgdbserver/deviceinfo/devices/atmega16hvbrevb.py
dwgdbserver/deviceinfo/devices/atmega16m1.py
dwgdbserver/deviceinfo/devices/atmega16u2.py
dwgdbserver/deviceinfo/devices/atmega328.py
dwgdbserver/deviceinfo/devices/atmega328p.py
dwgdbserver/deviceinfo/devices/atmega328pb.py
dwgdbserver/deviceinfo/devices/atmega32c1.py
dwgdbserver/deviceinfo/devices/atmega32hvb.py
dwgdbserver/deviceinfo/devices/atmega32hvbrevb.py
dwgdbserver/deviceinfo/devices/atmega32m1.py
dwgdbserver/deviceinfo/devices/atmega32u2.py
dwgdbserver/deviceinfo/devices/atmega48.py
dwgdbserver/deviceinfo/devices/atmega48a.py
dwgdbserver/deviceinfo/devices/atmega48p.py
dwgdbserver/deviceinfo/devices/atmega48pa.py
dwgdbserver/deviceinfo/devices/atmega48pb.py
dwgdbserver/deviceinfo/devices/atmega64c1.py
dwgdbserver/deviceinfo/devices/atmega64hve2.py
dwgdbserver/deviceinfo/devices/atmega64m1.py
dwgdbserver/deviceinfo/devices/atmega88.py
dwgdbserver/deviceinfo/devices/atmega88a.py
dwgdbserver/deviceinfo/devices/atmega88p.py
dwgdbserver/deviceinfo/devices/atmega88pa.py
dwgdbserver-2.3.2.dist-info/LICENSE
dwgdbserver-2.3.2.dist-info/METADATA
dwgdbserver-2.3.2.dist-info/WHEEL
dwgdbserver-2.3.2.dist-info/entry_points.txt
dwgdbserver-2.3.2.dist-info/RECORD
