Metadata-Version: 2.3
Name: dwgdbserver
Version: 2.3.2
Summary: A gdbserver for debugWIRE
License: MIT
Author: Bernhard Nebel
Author-email: nebel@arduino-craft-corner.de
Requires-Python: <3.14,>=3.9
Classifier: License :: OSI Approved :: MIT License
Classifier: Programming Language :: Python :: 3
Classifier: Programming Language :: Python :: 3.9
Classifier: Programming Language :: Python :: 3.10
Classifier: Programming Language :: Python :: 3.11
Classifier: Programming Language :: Python :: 3.12
Classifier: Programming Language :: Python :: 3.13
Requires-Dist: pexpect (>=4.9.0,<5.0.0)
Requires-Dist: pre-commit (>=4.2.0,<5.0.0)
Requires-Dist: pyedbglib (>=2.24.2.18,<3.0.0.0)
Requires-Dist: pyinstaller (>=6.12.0,<7.0.0)
Requires-Dist: pylint (>=3.3.6,<4.0.0)
Requires-Dist: pymcuprog (>=3.17.3.45,<4.0.0.0)
Requires-Dist: pyusb (>=1.3.1,<1.4.0)
Project-URL: Repository, https://github.com/felias-fogg/dw-gdbserver
